setup.py
aioimgbb/__init__.py
aioimgbb/client.py
aioimgbb/image.py
aioimgbb.egg-info/PKG-INFO
aioimgbb.egg-info/SOURCES.txt
aioimgbb.egg-info/dependency_links.txt
aioimgbb.egg-info/not-zip-safe
aioimgbb.egg-info/requires.txt
aioimgbb.egg-info/top_level.txt
tests/__init__.py
tests/upload.py