Metadata-Version: 1.0
Name: aioimgbb
Version: 1.0.0
Summary: No
Home-page: UNKNOWN
Author: UNKNOWN
Author-email: veenrokdalv@gmail.com
License: UNKNOWN
Platform: UNKNOWN
